pyhbst.cpython-313-x86_64-linux-gnu.so
pyhbst-0.2.0.dist-info/METADATA
pyhbst-0.2.0.dist-info/WHEEL
pyhbst-0.2.0.dist-info/top_level.txt
pyhbst-0.2.0.dist-info/RECORD
pyhbst-0.2.0.dist-info/licenses/LICENSE
